mathcli/__init__.py
mathcli/_unicode.py
mathcli/_utils.py
mathcli/cache.py
mathcli/cli.py
mathcli/errors.py
mathcli/expression.py
mathcli/math.py
mathcli/results.py
mathcli/theme.py
tests/__init__.py
tests/test_math.py
mathcli-0.1.dist-info/LICENSE
mathcli-0.1.dist-info/METADATA
mathcli-0.1.dist-info/WHEEL
mathcli-0.1.dist-info/entry_points.txt
mathcli-0.1.dist-info/top_level.txt
mathcli-0.1.dist-info/RECORD
